fakir/__init__.py
fakir/py.typed
fakir-0.1.dist-info/LICENSE
fakir-0.1.dist-info/METADATA
fakir-0.1.dist-info/WHEEL
fakir-0.1.dist-info/top_level.txt
fakir-0.1.dist-info/RECORD
