Metadata-Version: 2.1
Name: fakir
Version: 0.1
Summary: a mildly monadic module for fast faking
Home-page: https://github.com/derrickturk/fakir
Author: Derrick W. Turk
Author-email: dwt@terminusdatascience.com
License: UNKNOWN
Platform: UNKNOWN
Classifier: License :: OSI Approved :: Apache Software License
Classifier: Programming Language :: Python :: 3.6
Classifier: Programming Language :: Python :: 3.7
Classifier: Programming Language :: Python :: 3.8
Classifier: Operating System :: OS Independent
Requires-Python: >=3.6
